django_template_component/__about__.py
django_template_component/__init__.py
django_template_component/apps.py
django_template_component/loader.py
django_template_component/registry.py
django_template_component/template_component.py
django_template_component/test.py
django_template_component/templatetags/__init__.py
django_template_component/templatetags/component.py
django_template_component-0.0.1.dist-info/METADATA
django_template_component-0.0.1.dist-info/WHEEL
django_template_component-0.0.1.dist-info/licenses/LICENSE
django_template_component-0.0.1.dist-info/RECORD
