Metadata-Version: 2.4
Name: django-template-component
Version: 0.0.1
Project-URL: Documentation, https://github.com/bradshjg/django-template-component#readme
Project-URL: Issues, https://github.com/bradshjg/django-template-component/issues
Project-URL: Source, https://github.com/bradshjg/django-template-component
Author-email: James Bradshaw <james.g.bradshaw@gmail.com>
License-Expression: MIT
License-File: LICENSE
Classifier: Development Status :: 4 - Beta
Classifier: Programming Language :: Python
Classifier: Programming Language :: Python :: 3.10
Classifier: Programming Language :: Python :: 3.11
Classifier: Programming Language :: Python :: 3.12
Classifier: Programming Language :: Python :: 3.13
Requires-Python: >=3.8
Requires-Dist: django
Provides-Extra: test
Requires-Dist: beautifulsoup4; extra == 'test'
Requires-Dist: pytest-django~=4.11; extra == 'test'
Requires-Dist: pytest~=8.1; extra == 'test'
